lessgame/__init__.py
lessgame/functions.py
lessgame/gamegen.py
lessgame/gameutils.py
lessgame/rand.py
lessgame-1.0.4.dist-info/licenses/LICENSE
lessgame-1.0.4.dist-info/METADATA
lessgame-1.0.4.dist-info/WHEEL
lessgame-1.0.4.dist-info/top_level.txt
lessgame-1.0.4.dist-info/RECORD
