Metadata-Version: 2.4
Name: lessgame
Version: 1.0.4
Summary: Game logic for Less
Author-email: Mankifg <mankifg@gmail.com>
Project-URL: Homepage, https://github.com/Mankifg/LessLogic
Project-URL: Issues, https://github.com/Mankifg/LessLogic/issues
Classifier: Programming Language :: Python :: 3
Classifier: Operating System :: OS Independent
Requires-Python: >=3.9
License-File: LICENSE
Dynamic: license-file
